{
  "name": "Jesus Jennings",
  "age": 36,
  "address": {
    "street": "Cemduf River",
    "city": "Ubnowi",
    "state": "NC",
    "zip": "72361"
  },
  "contact": {
    "phone": "(415) 529-7142",
    "servicePhone": "800544139"
  },
  "birthday": "1975-06-09T20:33:43.997Z",
  "ip": "78.160.210.252",
  "foo": "bar",
  "profile": {
    "about": "Ag lij esunezpiz fara egbevho jojnifok ohukpud somahas luzda laki li focim facle tacohe dezama daz. Kuis rowat lendiju dihcewsas comnip wisi pe rervag zilu mopziz porooz se tano sohli ezubhu dukoh. Jazezde dowjectak ga ili mukipu fopbeag gopsakil ced ke uhfe rotinde migonutud puem ilinacac wif.",
    "bio": "Ro nobel iwjon ga ojakod fus geje bavubug cowto egidbel jehjofbe efpos fa jaita sagal. Dacan no catiz peccoos iv emizej dezilje hajjo jolha da ot hebud wislu. Emogeumu wi rak gotwos pufrumes agi hatibwik zohvaga fiivvof abi nat fu nic min. Obfizmi ku pewulbow iraishaz ramoeh ve avroz kup owhar ubozuzre igaseiza aklow rufidzat kad po. Aroba wujufdop med ilwahli mo fokwalmi nefcobki tikpa kizluz jel raho afgos semaema jeze ef cefducfu edoruc modode. Pop ehmojev ezsigup otmo zavfikca but agu ukidaclav vezehi ri cacujboz esefihha maszu jes obi uhoc."
  },
  "apiKey": "96e109f503d48ee36f698d607b05e56987c06f0dbc9717fb18b3db16878af057",
  "currency": {
    "code": "XCD",
    "name": "East Caribbean Dollar"
  }
}