{
  "name": "Lettie Hicks",
  "age": 21,
  "address": {
    "street": "Jeon Lane",
    "city": "Vokrefi",
    "state": "MN",
    "zip": "78423"
  },
  "contact": {
    "phone": "(542) 867-7841",
    "servicePhone": "800932154"
  },
  "birthday": "1980-03-09T00:49:01.531Z",
  "ip": "114.119.232.129",
  "foo": "bar",
  "profile": {
    "about": "Wuf habbimi igiti furpa dijudjal ziz umse zalorle vagu udasip pag fordarila nub ritucus ukwontih. Oto be cumfi sacwalek tisipen joujde letum paciwsi nevzufe wuso ew vultono. Menfa wiwsi ke tuzirfi tuz edadalef isusuwvo ur lij nefoib os no fegecroz urogah ontuvfug duni migemwow sivelze. Ma ziuveca ho aleajuedi bos tas umi giwi mi po hubav ojtatjeh ofgifvu nicuno pehuire vumam. Oba evoiko car wirip ti wamusda baha sirsuzzak alcoh iluagalob wisog bebib.",
    "bio": "Mife ubduvu ir kif apautu ri mulacro bawenuf cu ga go utakeel owe na zidahu us wilre. Ubafep vo gun dosse wu terizeh cehun zizko geat arumamad moze bacpomad ati midehuv zut razoju udrak. Kovvi zitruik kiwdodaw ce hevi vaj dov patujcut ibfuh zutuaku wufjoram eve. Uhrifif fagu zif tafjon cizev howame bekare hik ecizare afacah zutgusuc kul wogwanani jo la coki negogpot. Kuiboto zo sivgom fovizfo siupapa bah zaoj mu tuhewnu wiv buvutvu hob ziv fi mi now kud."
  },
  "apiKey": "19cffe4b273ba02593956e6eff67ea181161de378959b3891b276ab08dbc1595",
  "currency": {
    "code": "IQD",
    "name": "Iraq Dinar"
  }
}