{
  "name": "Ian Anderson",
  "age": 55,
  "address": {
    "street": "Dunba Plaza",
    "city": "Namipocu",
    "state": "ND",
    "zip": "52594"
  },
  "contact": {
    "phone": "(838) 529-3823",
    "servicePhone": "800611377"
  },
  "birthday": "2000-01-24T04:30:48.829Z",
  "ip": "232.54.202.22",
  "foo": "bar",
  "profile": {
    "about": "Il megil wewdo emeosagol zolmuga padedaz ram mo saca kob ra factob tita. Na wigodpo fida revtus soin jigig jeabtab fe fec zigsuad neapi ocvoapi jan marikip muehe. Ujeiruce ki uto ucuhujib manajni buuwpe wonehpiv nigmoz zi dafwecavi hor me puv aviuvga uge. San jogselow nif ro ceagupu ibawomup cokunid dimtu nized we evo jute bod. Akmibwel liwa sip bi oma folribij ruopauru ducrug belgamaf rab ided hawboh okowi jebutopa akledo. Gidaneb to defhizu japiug lulapva tacabbu varide fermabi mocre bubatgez icaahame supejelag rum. Nihlitku fa tikan po cijuwcit osli retebav dagiz dafo olu ruj ho sahlos nih ilkaw kipor ce pikheezo.",
    "bio": "Hubico sutos we ahupo jekojo sapfi pugzohsi pirpinsak gife bih ri rar cuwagicu noba ki otivijlog ho. Esot ikde kewu jociw nuvluz rofriled rak zodega heno fawana warwil betruw ranih bug tahharjik jumus ta tagopolik. Dan iha ohiaf da dufujoz ammamov wefiri edifu kalut otalo jici bigel fehregro molo."
  },
  "apiKey": "7d73bfc0db7df47f7a412fcd44c11dd6ef8eccb0418a074c90513c36b03b50d5",
  "currency": {
    "code": "STD",
    "name": "São Tomé and Príncipe Dobra"
  }
}