{
  "name": "Aiden Little",
  "age": 57,
  "address": {
    "street": "Ehemo Highway",
    "city": "Icabbok",
    "state": "FL",
    "zip": "14996"
  },
  "contact": {
    "phone": "(501) 418-1148",
    "servicePhone": "800232752"
  },
  "birthday": "1975-03-30T07:11:40.418Z",
  "ip": "199.217.54.110",
  "foo": "bar",
  "profile": {
    "about": "Arilat bu ozatobot boc oz fet joznig opsi wemnur la mo disjofoti pabal zaktarhof ke. Ilwe egu awewepnit emna vivi unju umna jeogu cuz vetdo opsa bupead ma. Epubim epuipeha imuhamnas wihe loel ruedaci zuzfu noru zuleuc rom awsi ufaripit cikor jer.",
    "bio": "Rouk mic vit zatja olwogdif elule gihnini talus kajmidgap fode muzre hoskobfut zonvawa po. Vajbut meufu wojatibow bet ada jalbuwoj ukfekabu selwoh cedah neci ca og giruca lubzak hebenoz zipubol rucniz. Kiusufu fitoj pemulfim rela acori koocu dip taz it isobiura gebfiuf mozev wado haw titet lote awfo."
  },
  "apiKey": "19305b58050579c52efa24c770b29e61da95e2f4d42a0f60e59736d4e98fd96a",
  "currency": {
    "code": "GYD",
    "name": "Guyana Dollar"
  }
}