{
  "name": "Adam McCoy",
  "age": 59,
  "address": {
    "street": "Jadlif Loop",
    "city": "Regifaz",
    "state": "TX",
    "zip": "54412"
  },
  "contact": {
    "phone": "(653) 599-6661",
    "servicePhone": "800427415"
  },
  "birthday": "1994-04-14T08:32:29.047Z",
  "ip": "86.134.179.109",
  "foo": "bar",
  "profile": {
    "about": "Me dacfukat ulovi wec fi weewi ogoc mukkepo agadeir cic gojwe suweku eri omhompuk cunkapigi jeg wohvevsif hij. Urolitaw wo fahjicu jugnuzca zujibhor wubate awvuj ig ukpezra kaj edlucfa samedeb wivcu elwezi waf wuldez wev. Lagul ti ru igwa abmaso ife okikej logusco irnefi uw tofri ebolim tifafta evfetzu ukeegese up. Kihtaru haoda lowepew fuz ogsonfo nicfib bokca zizilof zapbelu va ozajafam juj uc fupuhe oliilapo acbune.",
    "bio": "Mununtid dowtapzi mup vitvop tu fuse tew lehoremo pidas pica cimoh ojanimuf woceec mof wawinul wecjadaj. Juzzorek iruwif oskewko ussa pa duv ninguw vawmunta jilfe niz mecizkat uta fezzo. Ehaekowi cesane uda wit ebuozo dudwacziv bailacus awhaozi me led ji gep potuk jos unijtop me. Wehuh pajaj kecuf fajevuh nuw ne efvag nawwob mi fu bensic nu hiwiga hufolso ep. Puko luvsauzo piwrusuc ju li po igeizutap la ebe eblo hudita va hawoj rokes. Fura nogburah kizufdu kirmeh oz vifjuh esdo bekegri nojwova fabaoba uwukbe bugtieho nudof jo hoha rofrehjof hi aw."
  },
  "apiKey": "2942bebd2a5e38f41e5028fd9ac1ee8ff2d1c0f22e1bf8daf44d4ee992b33eca",
  "currency": {
    "code": "SYP",
    "name": "Syria Pound"
  }
}